fpd_data_processing/__init__.py
fpd_data_processing/api.py
fpd_data_processing/dummy_data.py
fpd_data_processing/io_tools.py
fpd_data_processing/lazy_tools.py
fpd_data_processing/make_diffraction_test_data.py
fpd_data_processing/pixelated_stem_class.py
fpd_data_processing/pixelated_stem_tools.py
fpd_data_processing/radial.py
fpd_data_processing-0.2.1.dist-info/DESCRIPTION.rst
fpd_data_processing-0.2.1.dist-info/METADATA
fpd_data_processing-0.2.1.dist-info/RECORD
fpd_data_processing-0.2.1.dist-info/WHEEL
fpd_data_processing-0.2.1.dist-info/metadata.json
fpd_data_processing-0.2.1.dist-info/top_level.txt
