Metadata-Version: 2.0
Name: fpd-data-processing
Version: 0.2.1
Summary: Library for processing scanning transmission electron microscopy data acquired using a fast pixelated detector
Home-page: UNKNOWN
Author: Magnus Nord
Author-email: magnunor@gmail.com
License: GPL v3
Keywords: STEM,data analysis,microscopy
Platform: UNKNOWN
Requires-Dist: dask
Requires-Dist: h5py
Requires-Dist: hyperspy (>=1.3)
Requires-Dist: ipython (>=2.0)
Requires-Dist: matplotlib (>=2.0)
Requires-Dist: numpy (>=1.10)
Requires-Dist: scipy
